{
  "schema_version": "environment-scenario-v0",
  "scenario_id": "source_body_opponent_overlap_kills_step",
  "title": "Source opponent body overlap kills step",
  "ruleset_id": "curvytron-v1-reference",
  "provenance": {
    "labels": [
      "source-derived",
      "body-collision",
      "source-body-canary"
    ],
    "source_target": "third_party/curvytron-reference",
    "source_commit": "8fec14c",
    "notes": [
      "Three-player source body-collision canary verified through the source-body-canary JS/Python runner.",
      "p0 starts at (20,20) in a 95-unit arena; a seeded p1 AvatarBody overlaps at (21.19,20) with radius 0.6 and kills p0.",
      "This fixture covers the strict-overlap kill side of the narrow source-body-canary contract."
    ]
  },
  "source_setup": {
    "player_count": 3,
    "map_size": 95,
    "random": {
      "math_random": 0.5
    },
    "room": {
      "name": "source-body-opponent-overlap-kills-step",
      "max_score": 10,
      "bonuses": [],
      "bonus_rate": 0
    },
    "game": {
      "started": true,
      "in_round": true,
      "borderless": false,
      "world_active": true
    }
  },
  "player_count": 3,
  "initial_state": {
    "world_bodies": [
      {
        "player_id": "p1",
        "x": 21.19,
        "y": 20,
        "radius": 0.6,
        "num": 0
      }
    ]
  },
  "time_policy": {
    "kind": "fixed",
    "step_ms": 0
  },
  "players": [
    {
      "id": "p0",
      "client_id": "p0-client",
      "avatar_id": 1,
      "name": "p0",
      "color": "#ff0000",
      "initial": {
        "x": 20,
        "y": 20,
        "angle_rad": 0,
        "printing": false
      }
    },
    {
      "id": "p1",
      "client_id": "p1-client",
      "avatar_id": 2,
      "name": "p1",
      "color": "#00ff00",
      "initial": {
        "x": 70,
        "y": 70,
        "angle_rad": 0,
        "printing": false
      }
    },
    {
      "id": "p2",
      "client_id": "p2-client",
      "avatar_id": 3,
      "name": "p2",
      "color": "#0000ff",
      "initial": {
        "x": 80,
        "y": 20,
        "angle_rad": 3.141592653589793,
        "printing": false
      }
    }
  ],
  "steps": [
    {
      "tick": 0,
      "step_ms": 0,
      "moves": [
        {
          "player_id": "p0",
          "move": 0
        },
        {
          "player_id": "p1",
          "move": 0
        },
        {
          "player_id": "p2",
          "move": 0
        }
      ]
    }
  ],
  "comparison": {
    "kind": "js-python-state-trace",
    "trace_schema_version": "environment-trace-v0",
    "include_events": true,
    "python_target": "source-body-canary",
    "source_fidelity_required": true,
    "tolerances": {
      "position": 0.000001,
      "angle": 0.000001,
      "velocity": 0.000001
    }
  }
}
